{
  "OrganizationName1077" : "Türk Dil Kurumu",
  "OrganizationName1733" : "Hoca sen emret",
  "PersonalName201" : "Albay Mehmet Emin",
  "PersonalName206" : "Emine Meliha",
  "PersonalName213" : "Turhan Bey",
  "PersonalName262" : "Dr. Alfred Heilbronn",
  "PersonalName480" : "Turhan Bey",
  "PersonalName612" : "Heilbronn",
  "PersonalName708" : "C. A. Mey",
  "PersonalName782" : "Asuman Hanım",
  "PersonalName1008" : "Asuman Baytop",
  "PersonalName1027" : "Davis",
  "PersonalName1051" : "Asuman",
  "PersonalName1104" : "Asuman Baytup",
  "PersonalName1105" : "Afife Mat",
  "PersonalName1359" : "Turhan Bey",
  "PersonalName1440" : "Turhan Bey",
  "PersonalName1456" : "Turhan Bey",
  "PersonalName1710" : "Seyit Ünsal",
  "PersonalName1720" : "Turhan Bey",
  "PersonalName1774" : "Ünsal",
  "PersonalName1834" : "Seyit Ünsal",
  "PersonalName1963" : "Dr.",
  "PersonalName1975" : "Asuman Hanım",
  "PersonalName1978" : "Turhan Bey",
  "PlaceName175" : "Turhan",
  "PlaceName198" : "Harput",
  "PlaceName204" : "Üsküdar",
  "PlaceName244" : "Erzurum",
  "PlaceName484" : "Palandöken Dağı",
  "PlaceName620" : "İstanbul",
  "PlaceName703" : "Heilbronn",
  "PlaceName932" : "Palandöken Dağı",
  "PlaceName1038" : "Edinburgh",
  "PlaceName1040" : "Kew",
  "PlaceName1195" : "Mathews",
  "PlaceName1205" : "Van",
  "PlaceName1206" : "Çatak",
  "PlaceName1301" : "Trabzon",
  "PlaceName1302" : "Artvin",
  "PlaceName1342" : "Trabzon",
  "PlaceName1363" : "Zigana Dağı",
  "PlaceName1965" : "Akdik",
  "PlaceName1968" : "Ord"
}