{
  "lemma1" : "Anadolu",
  "lemma2" : "bitki",
  "lemma3" : "Türkiye",
  "lemma4" : "ve",
  "lemma5" : "belirlemek",
  "lemma6" : "bilgi",
  "lemma7" : "ve",
  "lemma8" : "örnek",
  "lemma9" : "toplama",
  "lemma10" : "Anadolu",
  "lemma11" : "boyunca",
  "lemma12" : "kadar",
  "lemma13" : "bitki",
  "lemma14" : "renkli",
  "lemma15" : "fotoğraf",
  "lemma16" : "bir",
  "lemma17" : "bitki",
  "lemma18" : "Türkiye",
  "lemma19" : "ve",
  "lemma20" : "belirlemek",
  "lemma21" : "bilgi",
  "lemma22" : "ve",
  "lemma23" : "örnek",
  "lemma24" : "toplama",
  "lemma25" : "Anadolu",
  "lemma26" : "boyunca",
  "lemma27" : "kadar",
  "lemma28" : "bitki",
  "lemma29" : "renkli",
  "lemma30" : "fotoğraf",
  "lemma31" : "bir",
  "lemma32" : "bitki",
  "lemma33" : "Anadolu",
  "lemma34" : "bitki",
  "lemma35" : "bilim",
  "lemma36" : "yeni",
  "lemma37" : "yani",
  "lemma38" : "ilk",
  "lemma39" : "kez",
  "lemma40" : "o",
  "lemma41" : "Türkiye",
  "lemma42" : "ve",
  "lemma43" : "kadar",
  "lemma44" : "varmak",
  "lemma45" : "bir",
  "lemma46" : "diğer",
  "lemma47" : "ala",
  "lemma48" : "Türk",
  "lemma49" : "tarihî",
  "lemma50" : "ilk",
  "lemma51" : "tarihî",
  "lemma52" : "kişisel",
  "lemma53" : "oluşan",
  "lemma54" : "çekirdek",
  "lemma55" : "kurmak",
  "lemma56" : "haziran",
  "lemma57" : "dolduracak",
  "lemma58" : "yaş",
  "lemma59" : "devlet",
  "lemma60" : "o",
  "lemma61" : "emekli",
  "lemma62" : "etmek",
  "lemma63" : "ama",
  "lemma64" : "o",
  "lemma65" : "kendi",
  "lemma66" : "emekli",
  "lemma67" : "etmek",
  "lemma68" : "şu",
  "lemma69" : "yetiştirilen",
  "lemma70" : "gül",
  "lemma71" : "bir",
  "lemma72" : "bu",
  "lemma73" : "ve",
  "lemma74" : "dinç",
  "lemma75" : "bilim",
  "lemma76" : "ve",
  "lemma77" : "istemek",
  "lemma78" : "ve",
  "lemma79" : "Asuman",
  "lemma80" : "ve",
  "lemma81" : "geçmiş",
  "lemma82" : "Ömer",
  "lemma83" : "haziran",
  "lemma84" : "Üsküdar",
  "lemma85" : "Harput",
  "lemma86" : "doğumlu",
  "lemma87" : "topçu",
  "lemma88" : "albay",
  "lemma89" : "Mehmet",
  "lemma90" : "Üsküdar",
  "lemma91" : "doğumlu",
  "lemma92" : "Emine",
  "lemma93" : "isimli",
  "lemma94" : "bir",
  "lemma95" : "varmak",
  "lemma96" : "bey",
  "lemma97" : "Anadolu",
  "lemma98" : "daha",
  "lemma99" : "çocukken",
  "lemma100" : "düşünmek",
  "lemma101" : "gezen",
  "lemma102" : "bir",
  "lemma103" : "o",
  "lemma104" : "Erzurum",
  "lemma105" : "sonra",
  "lemma106" : "girmek",
  "lemma107" : "en",
  "lemma108" : "çok",
  "lemma109" : "verilen",
  "lemma110" : "botanik",
  "lemma111" : "ve",
  "lemma112" : "verilen",
  "lemma113" : "botanik",
  "lemma114" : "o",
  "lemma115" : "Hitler",
  "lemma116" : "kaçan",
  "lemma117" : "çok",
  "lemma118" : "Alman",
  "lemma119" : "bilim",
  "lemma120" : "da",
  "lemma121" : "o",
  "lemma122" : "Anadolu",
  "lemma123" : "birçok",
  "lemma124" : "gezgin",
  "lemma125" : "ve",
  "lemma126" : "söz",
  "lemma127" : "hiçbir",
  "lemma128" : "Türk",
  "lemma129" : "baş",
  "lemma130" : "olmak",
  "lemma131" : "üzer",
  "lemma132" : "üzmek",
  "lemma133" : "yine",
  "lemma134" : "ders",
  "lemma135" : "olarak",
  "lemma136" : "okutulan",
  "lemma137" : "isimli",
  "lemma138" : "da",
  "lemma139" : "hiçbir",
  "lemma140" : "Türk",
  "lemma141" : "Alman",
  "lemma142" : "olarak",
  "lemma143" : "söz",
  "lemma144" : "Anadolu",
  "lemma145" : "en",
  "lemma146" : "az",
  "lemma147" : "beri",
  "lemma148" : "ve",
  "lemma149" : "ilaç",
  "lemma150" : "olarak",
  "lemma151" : "Anadolu",
  "lemma152" : "hemen",
  "lemma153" : "hemen",
  "lemma154" : "hiç",
  "lemma155" : "bu",
  "lemma156" : "görev",
  "lemma157" : "veya",
  "lemma158" : "hiçbir",
  "lemma159" : "yeni",
  "lemma160" : "bitki",
  "lemma161" : "bu",
  "lemma162" : "Doğu",
  "lemma163" : "tek",
  "lemma164" : "önemli",
  "lemma165" : "kaynak",
  "lemma166" : "olan",
  "lemma167" : "botanikçi",
  "lemma168" : "ciltlik",
  "lemma169" : "de",
  "lemma170" : "bitki",
  "lemma171" : "tür",
  "lemma172" : "tek",
  "lemma173" : "bir",
  "lemma174" : "Türk",
  "lemma175" : "demek",
  "lemma176" : "bitki",
  "lemma177" : "henüz",
  "lemma178" : "öğrenciyken",
  "lemma179" : "bitki",
  "lemma180" : "toplama",
  "lemma181" : "henüz",
  "lemma182" : "öğrenciyken",
  "lemma183" : "eylül",
  "lemma184" : "o",
  "lemma185" : "Erzurum",
  "lemma186" : "görev",
  "lemma187" : "görevli",
  "lemma188" : "bir",
  "lemma189" : "gün",
  "lemma190" : "yer",
  "lemma191" : "istemek",
  "lemma192" : "söylemek",
  "lemma193" : "oğul",
  "lemma194" : "bey",
  "lemma195" : "etmek",
  "lemma196" : "tamamen",
  "lemma197" : "ve",
  "lemma198" : "çiçekli",
  "lemma199" : "bitki",
  "lemma200" : "bir",
  "lemma201" : "süre",
  "lemma202" : "sonra",
  "lemma203" : "kurt",
  "lemma204" : "ya",
  "lemma205" : "da",
  "lemma206" : "denilen",
  "lemma207" : "bir",
  "lemma208" : "durmak",
  "lemma209" : "eylül",
  "lemma210" : "bir",
  "lemma211" : "güneş",
  "lemma212" : "bir",
  "lemma213" : "bir",
  "lemma214" : "miktar",
  "lemma215" : "örnek",
  "lemma216" : "süt",
  "lemma217" : "her",
  "lemma218" : "dip",
  "lemma219" : "iki",
  "lemma220" : "leke",
  "lemma221" : "bu",
  "lemma222" : "ilk",
  "lemma223" : "örnek",
  "lemma224" : "Anadolu",
  "lemma225" : "ilk",
  "lemma226" : "ve",
  "lemma227" : "kişisel",
  "lemma228" : "örnek",
  "lemma229" : "olarak",
  "lemma230" : "son",
  "lemma231" : "boş",
  "lemma232" : "veya",
  "lemma233" : "ve",
  "lemma234" : "botanik",
  "lemma235" : "gördük",
  "lemma236" : "Türkiye",
  "lemma237" : "resmi",
  "lemma238" : "bir",
  "lemma239" : "uygun",
  "lemma240" : "düşünerek",
  "lemma241" : "önce",
  "lemma242" : "doçent",
  "lemma243" : "olan",
  "lemma244" : "sonra",
  "lemma245" : "olarak",
  "lemma246" : "etmek",
  "lemma247" : "ve",
  "lemma248" : "yetişen",
  "lemma249" : "tür",
  "lemma250" : "ertesi",
  "lemma251" : "gün",
  "lemma252" : "haziran",
  "lemma253" : "sonra",
  "lemma254" : "gitmek",
  "lemma255" : "askerlik",
  "lemma256" : "tümen",
  "lemma257" : "ay",
  "lemma258" : "yaparak",
  "lemma259" : "bitki",
  "lemma260" : "ve",
  "lemma261" : "tayin",
  "lemma262" : "tür",
  "lemma263" : "bu",
  "lemma264" : "ufak",
  "lemma265" : "Türkiye",
  "lemma266" : "ilk",
  "lemma267" : "sonra",
  "lemma268" : "ve",
  "lemma269" : "teğmen",
  "lemma270" : "olarak",
  "lemma271" : "terhis",
  "lemma272" : "olur",
  "lemma273" : "tayin",
  "lemma274" : "olur",
  "lemma275" : "ve",
  "lemma276" : "mey",
  "lemma277" : "in",
  "lemma278" : "morfolojik",
  "lemma279" : "anatomik",
  "lemma280" : "ve",
  "lemma281" : "kimyasal",
  "lemma282" : "isimli",
  "lemma283" : "doktor",
  "lemma284" : "Paris",
  "lemma285" : "görgü",
  "lemma286" : "ve",
  "lemma287" : "Anadolu",
  "lemma288" : "kök",
  "lemma289" : "ve",
  "lemma290" : "isimli",
  "lemma291" : "üniversite",
  "lemma292" : "da",
  "lemma293" : "eylemli",
  "lemma294" : "yine",
  "lemma295" : "gibi",
  "lemma296" : "doçent",
  "lemma297" : "olan",
  "lemma298" : "Asuman",
  "lemma299" : "Asuman",
  "lemma300" : "Anadolu",
  "lemma301" : "avlanma",
  "lemma302" : "en",
  "lemma303" : "olacak",
  "lemma304" : "ve",
  "lemma305" : "bu",
  "lemma306" : "toplanan",
  "lemma307" : "bitki",
  "lemma308" : "hemen",
  "lemma309" : "tayin",
  "lemma310" : "çift",
  "lemma311" : "ve",
  "lemma312" : "beraber",
  "lemma313" : "çok",
  "lemma314" : "Feza",
  "lemma315" : "bir",
  "lemma316" : "olur",
  "lemma317" : "Feza",
  "lemma318" : "bugün",
  "lemma319" : "bilim",
  "lemma320" : "tarihî",
  "lemma321" : "olarak",
  "lemma322" : "görev",
  "lemma323" : "dek",
  "lemma324" : "değişik",
  "lemma325" : "tarih",
  "lemma326" : "bu",
  "lemma327" : "dönem",
  "lemma328" : "anabilim",
  "lemma329" : "yaş",
  "lemma330" : "emekli",
  "lemma331" : "olur",
  "lemma332" : "ama",
  "lemma333" : "kadar",
  "lemma334" : "tarihî",
  "lemma335" : "ve",
  "lemma336" : "deva",
  "lemma337" : "etmek",
  "lemma338" : "sonra",
  "lemma339" : "ilk",
  "lemma340" : "son",
  "lemma341" : "akademik",
  "lemma342" : "boyunca",
  "lemma343" : "ve",
  "lemma344" : "emekli",
  "lemma345" : "sonra",
  "lemma346" : "bitki",
  "lemma347" : "ki",
  "lemma348" : "pazar",
  "lemma349" : "dek",
  "lemma350" : "bu",
  "lemma351" : "tarih",
  "lemma352" : "bitki",
  "lemma353" : "toplama",
  "lemma354" : "kendi",
  "lemma355" : "tekrar",
  "lemma356" : "ziyaret",
  "lemma357" : "etmek",
  "lemma358" : "bu",
  "lemma359" : "Anadolu",
  "lemma360" : "örnek",
  "lemma361" : "toplama",
  "lemma362" : "önce",
  "lemma363" : "son",
  "lemma364" : "olur",
  "lemma365" : "gezilerdeki",
  "lemma366" : "yerli",
  "lemma367" : "ad",
  "lemma368" : "ve",
  "lemma369" : "saptama",
  "lemma370" : "ve",
  "lemma371" : "zehirli",
  "lemma372" : "belirlemek",
  "lemma373" : "Türkiye",
  "lemma374" : "yetişen",
  "lemma375" : "her",
  "lemma376" : "türlü",
  "lemma377" : "ve",
  "lemma378" : "özellik",
  "lemma379" : "toplamak",
  "lemma380" : "ve",
  "lemma381" : "yetiştirme",
  "lemma382" : "ve",
  "lemma383" : "yöresel",
  "lemma384" : "yerli",
  "lemma385" : "ve",
  "lemma386" : "yabani",
  "lemma387" : "Anadolu",
  "lemma388" : "her",
  "lemma389" : "örnek",
  "lemma390" : "Asuman",
  "lemma391" : "olan",
  "lemma392" : "çift",
  "lemma393" : "olan",
  "lemma394" : "bir",
  "lemma395" : "Davis",
  "lemma396" : "yürütülen",
  "lemma397" : "in",
  "lemma398" : "bulunmak",
  "lemma399" : "Edinburgh",
  "lemma400" : "ve",
  "lemma401" : "in",
  "lemma402" : "cilt",
  "lemma403" : "Asuman",
  "lemma404" : "ve",
  "lemma405" : "ithaf",
  "lemma406" : "sonunda",
  "lemma407" : "kadar",
  "lemma408" : "bitki",
  "lemma409" : "tür",
  "lemma410" : "ait",
  "lemma411" : "Türkçe",
  "lemma412" : "bitki",
  "lemma413" : "bu",
  "lemma414" : "bitki",
  "lemma415" : "Türk",
  "lemma416" : "dil",
  "lemma417" : "Türkçe",
  "lemma418" : "bitki",
  "lemma419" : "yer",
  "lemma420" : "yine",
  "lemma421" : "bu",
  "lemma422" : "son",
  "lemma423" : "saptanan",
  "lemma424" : "kadar",
  "lemma425" : "zehirli",
  "lemma426" : "bitki",
  "lemma427" : "tür",
  "lemma428" : "ve",
  "lemma429" : "toplanan",
  "lemma430" : "Asuman",
  "lemma431" : "mat",
  "lemma432" : "ve",
  "lemma433" : "birlik",
  "lemma434" : "Türkiye",
  "lemma435" : "zehirli",
  "lemma436" : "bitki",
  "lemma437" : "ve",
  "lemma438" : "tedavi",
  "lemma439" : "yeni",
  "lemma440" : "bir",
  "lemma441" : "tür",
  "lemma442" : "dek",
  "lemma443" : "yeni",
  "lemma444" : "bir",
  "lemma445" : "tür",
  "lemma446" : "yüksek",
  "lemma447" : "bir",
  "lemma448" : "veya",
  "lemma449" : "bir",
  "lemma450" : "orman",
  "lemma451" : "bir",
  "lemma452" : "tür",
  "lemma453" : "yeni",
  "lemma454" : "bir",
  "lemma455" : "tür",
  "lemma456" : "fakat",
  "lemma457" : "bir",
  "lemma458" : "son",
  "lemma459" : "tür",
  "lemma460" : "çok",
  "lemma461" : "önce",
  "lemma462" : "toplanarak",
  "lemma463" : "anlayarak",
  "lemma464" : "yani",
  "lemma465" : "yeni",
  "lemma466" : "tür",
  "lemma467" : "daima",
  "lemma468" : "geç",
  "lemma469" : "bu",
  "lemma470" : "bekleyiş",
  "lemma471" : "işleyen",
  "lemma472" : "ve",
  "lemma473" : "isimli",
  "lemma474" : "iki",
  "lemma475" : "ağustos",
  "lemma476" : "günü",
  "lemma477" : "Van",
  "lemma478" : "bir",
  "lemma479" : "geven",
  "lemma480" : "tür",
  "lemma481" : "yeni",
  "lemma482" : "bir",
  "lemma483" : "tür",
  "lemma484" : "olarak",
  "lemma485" : "son",
  "lemma486" : "bilim",
  "lemma487" : "yeni",
  "lemma488" : "tür",
  "lemma489" : "ilk",
  "lemma490" : "bitki",
  "lemma491" : "toplama",
  "lemma492" : "tür",
  "lemma493" : "bu",
  "lemma494" : "da",
  "lemma495" : "o",
  "lemma496" : "bu",
  "lemma497" : "tür",
  "lemma498" : "olan",
  "lemma499" : "Asuman",
  "lemma500" : "ve",
  "lemma501" : "tarih",
  "lemma502" : "gösteren",
  "lemma503" : "Anadolu",
  "lemma504" : "neredeyse",
  "lemma505" : "yer",
  "lemma506" : "düşünmek",
  "lemma507" : "kadar",
  "lemma508" : "üstelik",
  "lemma509" : "bu",
  "lemma510" : "il",
  "lemma511" : "günü",
  "lemma512" : "birlik",
  "lemma513" : "kim",
  "lemma514" : "birçok",
  "lemma515" : "defa",
  "lemma516" : "gerekmek",
  "lemma517" : "Trabzon",
  "lemma518" : "Artvin",
  "lemma519" : "tam",
  "lemma520" : "defa",
  "lemma521" : "gitmek",
  "lemma522" : "ya",
  "lemma523" : "bilgi",
  "lemma524" : "ve",
  "lemma525" : "tür",
  "lemma526" : "ilk",
  "lemma527" : "ya",
  "lemma528" : "da",
  "lemma529" : "değişik",
  "lemma530" : "cahil",
  "lemma531" : "otelci",
  "lemma532" : "ve",
  "lemma533" : "öğrenci",
  "lemma534" : "çok",
  "lemma535" : "Trabzon",
  "lemma536" : "bir",
  "lemma537" : "o",
  "lemma538" : "genellik",
  "lemma539" : "kamyon",
  "lemma540" : "otel",
  "lemma541" : "bey",
  "lemma542" : "otel",
  "lemma543" : "ve",
  "lemma544" : "olacak",
  "lemma545" : "bir",
  "lemma546" : "rehber",
  "lemma547" : "söylemek",
  "lemma548" : "otel",
  "lemma549" : "hoca",
  "lemma550" : "müşteri",
  "lemma551" : "her",
  "lemma552" : "zaman",
  "lemma553" : "varmak",
  "lemma554" : "sen",
  "lemma555" : "bir",
  "lemma556" : "gelmek",
  "lemma557" : "zaten",
  "lemma558" : "gündüzleri",
  "lemma559" : "kimse",
  "lemma560" : "sabah",
  "lemma561" : "ben",
  "lemma562" : "otel",
  "lemma563" : "ve",
  "lemma564" : "birlikte",
  "lemma565" : "olur",
  "lemma566" : "gerçekten",
  "lemma567" : "de",
  "lemma568" : "ertesi",
  "lemma569" : "sabah",
  "lemma570" : "otel",
  "lemma571" : "birlikte",
  "lemma572" : "bütün",
  "lemma573" : "gün",
  "lemma574" : "yine",
  "lemma575" : "öğrenci",
  "lemma576" : "olan",
  "lemma577" : "oğul",
  "lemma578" : "bu",
  "lemma579" : "genç",
  "lemma580" : "genç",
  "lemma581" : "o",
  "lemma582" : "ben",
  "lemma583" : "kaç",
  "lemma584" : "para",
  "lemma585" : "diye",
  "lemma586" : "bey",
  "lemma587" : "kendi",
  "lemma588" : "verebilecek",
  "lemma589" : "bir",
  "lemma590" : "söylemek",
  "lemma591" : "genç",
  "lemma592" : "bey",
  "lemma593" : "bu",
  "lemma594" : "iki",
  "lemma595" : "cahil",
  "lemma596" : "bir",
  "lemma597" : "otelci",
  "lemma598" : "üniversite",
  "lemma599" : "olarak",
  "lemma600" : "bir",
  "lemma601" : "kişi",
  "lemma602" : "fark",
  "lemma603" : "diye",
  "lemma604" : "yöredeki",
  "lemma605" : "botanik",
  "lemma606" : "zooloji",
  "lemma607" : "gibi",
  "lemma608" : "yerli",
  "lemma609" : "ilgi",
  "lemma610" : "duyan",
  "lemma611" : "çok",
  "lemma612" : "insan",
  "lemma613" : "eşlik",
  "lemma614" : "etmek",
  "lemma615" : "Anadolu",
  "lemma616" : "bitki",
  "lemma617" : "avlama",
  "lemma618" : "tek",
  "lemma619" : "tek",
  "lemma620" : "bilgi",
  "lemma621" : "ve",
  "lemma622" : "teşekkür",
  "lemma623" : "fakülte",
  "lemma624" : "de",
  "lemma625" : "bitki",
  "lemma626" : "gezi",
  "lemma627" : "özellik",
  "lemma628" : "Edirne",
  "lemma629" : "Kars",
  "lemma630" : "kadar",
  "lemma631" : "birlikte",
  "lemma632" : "ve",
  "lemma633" : "güç",
  "lemma634" : "aşarak",
  "lemma635" : "ve",
  "lemma636" : "yay",
  "lemma637" : "köy",
  "lemma638" : "bir",
  "lemma639" : "karakter",
  "lemma640" : "ve",
  "lemma641" : "yaşanılan",
  "lemma642" : "ve",
  "lemma643" : "bu",
  "lemma644" : "tutu",
  "lemma645" : "ve",
  "lemma646" : "görerek",
  "lemma647" : "demek",
  "lemma648" : "ve",
  "lemma649" : "ilgili",
  "lemma650" : "birkaç",
  "lemma651" : "Anadolu",
  "lemma652" : "uzak",
  "lemma653" : "tertiplenen",
  "lemma654" : "biz",
  "lemma655" : "toplanan",
  "lemma656" : "sonradan",
  "lemma657" : "araba",
  "lemma658" : "yani",
  "lemma659" : "tek",
  "lemma660" : "alma",
  "lemma661" : "değer",
  "lemma662" : "nokta",
  "lemma663" : "bu",
  "lemma664" : "tek",
  "lemma665" : "ben",
  "lemma666" : "araba",
  "lemma667" : "Van",
  "lemma668" : "yol",
  "lemma669" : "boyunca",
  "lemma670" : "görüp",
  "lemma671" : "değer",
  "lemma672" : "belki",
  "lemma673" : "Asuman",
  "lemma674" : "iş",
  "lemma675" : "yarar",
  "lemma676" : "etiketleyip",
  "lemma677" : "ve",
  "lemma678" : "biz",
  "lemma679" : "bu",
  "lemma680" : "değer",
  "lemma681" : "ve",
  "lemma682" : "öğreti",
  "lemma683" : "birlik",
  "lemma684" : "yaz",
  "lemma685" : "ilgili",
  "lemma686" : "konu",
  "lemma687" : "belirli",
  "lemma688" : "bir",
  "lemma689" : "miktar",
  "lemma690" : "para",
  "lemma691" : "verme",
  "lemma692" : "konu",
  "lemma693" : "daha",
  "lemma694" : "iyi",
  "lemma695" : "demek",
  "lemma696" : "bitki",
  "lemma697" : "toplamak",
  "lemma698" : "Doğu",
  "lemma699" : "Anadolu",
  "lemma700" : "gerekmek",
  "lemma701" : "bu",
  "lemma702" : "emekli",
  "lemma703" : "ve",
  "lemma704" : "yer",
  "lemma705" : "yeni",
  "lemma706" : "bir",
  "lemma707" : "şoför",
  "lemma708" : "de",
  "lemma709" : "bey",
  "lemma710" : "bir",
  "lemma711" : "haf",
  "lemma712" : "Doğu",
  "lemma713" : "Anadolu",
  "lemma714" : "gelip",
  "lemma715" : "cevap",
  "lemma716" : "hoca",
  "lemma717" : "sen",
  "lemma718" : "emretmek",
  "lemma719" : "ben",
  "lemma720" : "girmek",
  "lemma721" : "olur",
  "lemma722" : "bu",
  "lemma723" : "cevap",
  "lemma724" : "bir",
  "lemma725" : "beraber",
  "lemma726" : "en",
  "lemma727" : "büyük",
  "lemma728" : "demek",
  "lemma729" : "ama",
  "lemma730" : "gezi",
  "lemma731" : "bir",
  "lemma732" : "kaz",
  "lemma733" : "olur",
  "lemma734" : "ve",
  "lemma735" : "hasar",
  "lemma736" : "bu",
  "lemma737" : "emekli",
  "lemma738" : "olan",
  "lemma739" : "uzun",
  "lemma740" : "sonuç",
  "lemma741" : "dekan",
  "lemma742" : "gelecek",
  "lemma743" : "her",
  "lemma744" : "türlü",
  "lemma745" : "sorumlu",
  "lemma746" : "dair",
  "lemma747" : "bir",
  "lemma748" : "senet",
  "lemma749" : "sonra",
  "lemma750" : "bitki",
  "lemma751" : "toplama",
  "lemma752" : "ilgili",
  "lemma753" : "hale",
  "lemma754" : "âdet",
  "lemma755" : "fazla",
  "lemma756" : "örnek",
  "lemma757" : "ve",
  "lemma758" : "Türkiye",
  "lemma759" : "en",
  "lemma760" : "zengin",
  "lemma761" : "olan",
  "lemma762" : "yararlanan",
  "lemma763" : "her",
  "lemma764" : "bu",
  "lemma765" : "ne",
  "lemma766" : "gibi",
  "lemma767" : "ve",
  "lemma768" : "gibi",
  "lemma769" : "birçok",
  "lemma770" : "diyerek",
  "lemma771" : "evdeki",
  "lemma772" : "müze",
  "lemma773" : "an",
  "lemma774" : "bitki",
  "lemma775" : "değil",
  "lemma776" : "her",
  "lemma777" : "tarihî",
  "lemma778" : "yani",
  "lemma779" : "çeşitli",
  "lemma780" : "dolu",
  "lemma781" : "üstündeki",
  "lemma782" : "kalma",
  "lemma783" : "ve",
  "lemma784" : "toprak",
  "lemma785" : "demek",
  "lemma786" : "eski",
  "lemma787" : "gitmek",
  "lemma788" : "ilgili",
  "lemma789" : "tarihî",
  "lemma790" : "araç",
  "lemma791" : "gereç",
  "lemma792" : "tarihî",
  "lemma793" : "yer",
  "lemma794" : "bilen",
  "lemma795" : "eş",
  "lemma796" : "dost",
  "lemma797" : "hediye",
  "lemma798" : "demek",
  "lemma799" : "orijinal",
  "lemma800" : "kuş",
  "lemma801" : "varmak",
  "lemma802" : "Türkiye",
  "lemma803" : "Alman",
  "lemma804" : "bir",
  "lemma805" : "hayvan",
  "lemma806" : "yine",
  "lemma807" : "duvarlardaki",
  "lemma808" : "Türkiye",
  "lemma809" : "bitki",
  "lemma810" : "de",
  "lemma811" : "orijinal",
  "lemma812" : "zaten",
  "lemma813" : "ben",
  "lemma814" : "Türkiye",
  "lemma815" : "ait",
  "lemma816" : "olmayan",
  "lemma817" : "bir",
  "lemma818" : "uğraşma",
  "lemma819" : "istemek",
  "lemma820" : "demek",
  "lemma821" : "bir",
  "lemma822" : "de",
  "lemma823" : "portre",
  "lemma824" : "varmak",
  "lemma825" : "resmi",
  "lemma826" : "hem",
  "lemma827" : "Asuman",
  "lemma828" : "hem",
  "lemma829" : "de",
  "lemma830" : "bey",
  "lemma831" : "asistan",
  "lemma832" : "olmak",
  "lemma833" : "Almanya",
  "lemma834" : "mezar",
  "lemma835" : "Türkiye",
  "lemma836" : "hizmet",
  "lemma837" : "etmek",
  "lemma838" : "ay"
}